lightprotobufgen/__init__.py
lightprotobufgen/protobufParser.py
lightprotobufgen/protobufListener.py
lightprotobufgen/lightprotobufgen.py
lightprotobufgen/protobufLexer.py
lightprotobufgen-1.0.dev0.dist-info/DESCRIPTION.rst
lightprotobufgen-1.0.dev0.dist-info/metadata.json
lightprotobufgen-1.0.dev0.dist-info/entry_points.txt
lightprotobufgen-1.0.dev0.dist-info/RECORD
lightprotobufgen-1.0.dev0.dist-info/top_level.txt
lightprotobufgen-1.0.dev0.dist-info/METADATA
lightprotobufgen-1.0.dev0.dist-info/WHEEL
