Metadata-Version: 2.0
Name: lightprotobufgen
Version: 1.0.dev0
Summary: A Script to translate .proto files to lightprotobuf messages
Home-page: https://github.com/hl037/lightprotobuf
Author: Léo Flaventin Hauchecorne
Author-email: hl037.prog@gmail.com
License: LGPL3
Keywords: protobuf protocol buffers communication
Platform: UNKNOWN
Classifier: Development Status :: 2 - Pre-Alpha
Classifier: Intended Audience :: Developers
Classifier: Topic :: Communications
Classifier: Topic :: Internet
Classifier: License :: OSI Approved :: GNU General Public License v3 or later (GPLv3+)
Classifier: Programming Language :: Python :: 3
Classifier: Programming Language :: Python :: 3.2
Classifier: Programming Language :: Python :: 3.3
Classifier: Programming Language :: Python :: 3.4
Classifier: Programming Language :: Python :: 3 :: Only
Requires-Dist: antlr4-python3-runtime (>=4.5)
